dice_parser/__init__.py
dice_parser/dice_roller.py
dice_parser/modifier.py
dice_parser/parser.py
dice_parser/parser_result.py
dice_parser/transformer.py
dice_parser-1.0.dist-info/METADATA
dice_parser-1.0.dist-info/WHEEL
dice_parser-1.0.dist-info/top_level.txt
dice_parser-1.0.dist-info/RECORD
